dell_api/__init__.py
dell_api/__main__.py
dell_warranty_api-1.10.0.dist-info/METADATA
dell_warranty_api-1.10.0.dist-info/WHEEL
dell_warranty_api-1.10.0.dist-info/entry_points.txt
dell_warranty_api-1.10.0.dist-info/top_level.txt
dell_warranty_api-1.10.0.dist-info/RECORD
