Metadata-Version: 2.1
Name: dell-warranty-api
Version: 1.10.0
Summary: Receive info about dell devices in humanize view
Home-page: https://github.com/karma-git/dell_warranty_status_api
Author: karma_
Author-email: andrewhorbach@gmail.com
License: MIT
Platform: UNKNOWN
Classifier: License :: OSI Approved :: MIT License
Classifier: Programming Language :: Python :: 3
Classifier: Programming Language :: Python :: 3.9
Requires-Dist: requests
Requires-Dist: pycountry
Requires-Dist: prettytable
Requires-Dist: humanize
Requires-Dist: loguru
Requires-Dist: pretty-errors
